just_agents/web/__init__.py
just_agents/web/chat_ui.py
just_agents/web/chat_ui_agent.py
just_agents/web/chat_ui_rest_api.py
just_agents/web/config.py
just_agents/web/deploy_agent.py
just_agents/web/models.py
just_agents/web/rest_api.py
just_agents/web/run_agent.py
just_agents/web/streaming.py
just_agents/web/web_agent.py
just_agents_web-0.8.7.dist-info/METADATA
just_agents_web-0.8.7.dist-info/WHEEL
just_agents_web-0.8.7.dist-info/entry_points.txt
just_agents_web-0.8.7.dist-info/RECORD
