Metadata-Version: 2.4
Name: just-agents-web
Version: 0.8.7
Summary: Just Agents - Web. It allows runing openai API for the agent in the browser.
License: MIT
Keywords: python,llm,web,agents,AI
Author: Alex Karmazin
Author-email: karmazinalex@gmail.com
Maintainer: Anton Kulaga
Maintainer-email: antonkulaga@gmail.com
Requires-Python: >=3.10,<3.15
Classifier: Development Status :: 2 - Pre-Alpha
Classifier: Intended Audience :: Developers
Classifier: License :: OSI Approved :: MIT License
Classifier: Operating System :: MacOS :: MacOS X
Classifier: Operating System :: Microsoft :: Windows
Classifier: Operating System :: Unix
Classifier: Programming Language :: Python :: 3
Classifier: Programming Language :: Python :: 3.10
Classifier: Programming Language :: Python :: 3.11
Classifier: Programming Language :: Python :: 3.12
Classifier: Programming Language :: Python :: 3.13
Classifier: Programming Language :: Python :: 3.14
Requires-Dist: aiofiles (>=24.1.0)
Requires-Dist: fastapi (>=0.115.12)
Requires-Dist: just-agents-core
Requires-Dist: pycomfort (>=0.0.18)
Requires-Dist: python-dotenv (>=1.1.0)
Requires-Dist: uvicorn (>=0.34.0)
